confiture
