Metadata-Version: 1.1
Name: spread-confiture
Version: 0.17.3rc1
Summary: A checker for required fields in yaml files
Home-page: https://github.com/Frky/confiture
Author: _Frky
Author-email: francky.dg@gmail.com
License: MIT
Keywords: yaml configuration config required fields template
Platform: UNKNOWN
Classifier: Development Status :: 4 - Beta
Classifier: Intended Audience :: Developers
Classifier: Topic :: Software Development :: Testing
Classifier: License :: OSI Approved :: MIT License
